{    
    "name": "Coral Squid",
    "icon": "minecraft:water_bucket",
    "category": "patchouli:creatures",
    "sortnum": 0,
    "advancement": "endernomicon:coral_squid",
    "pages": [
        {
            "type": "patchouli:text",
            "text": "$(li)Coral Squids are a type of cephalopods that likes to hang out around corals in $(l:patchouli:biomes/overworld/water/warm_ocean)Warm Oceans$(/l).$(br)$(li)They have 5 different colors $(li)Yellow $(li)Red $(li)Pink $(li)Purple $(li)Blue"
        },
        {
            "type": "patchouli:entity",
            "entity": "charm:coral_squid",
            "scale": 1,
            "offset": -0.6,
            "text": "They may drop their corresponding coral color on death."
        }
             ]
}
