{    
    "name": "Chainmail Armor",
    "icon": "minecraft:chainmail_helmet",
    "category": "patchouli:armors",
    "sortnum": 4,
    "advancement": "endernomicon:chainmail_armor",
    "pages": [
        {
            "type": "patchouli:text",
            "text": "$(li)The Chainmail Armor is a bit better than the $(l:patchouli:armors/ice_armor)Ice Armor$(/l).$(br)$(li)$(l:patchouli:villagers/armorer)Armorers$(/l) will exchange pieces of this armor for $(l:patchouli:miscellaneous/vanilla/emerald)Emeralds$(/l)."
        },
        {
            "type": "patchouli:entity",
            "name": "Chainmail Armor",
            "entity": "minecraft:armor_stand{ShowArms:1b,NoBasePlate:1b,ArmorItems:[{id:chainmail_boots,Count:1},{id:chainmail_leggings,Count:1},{id:chainmail_chestplate,Count:1},{id:chainmail_helmet,Count:1}],ArmorDropChances:[0f,0f,0f,0f]}"
        },
        {
            "type": "patchouli:spotlight",
            "item": "minecraft:chainmail_helmet",
            "link_recipe": "true"
        },
        {
            "type": "patchouli:spotlight",
            "item":"minecraft:chainmail_chestplate",
            "link_recipe": "true"
        },
        {
            "type": "patchouli:spotlight",
            "item": "minecraft:chainmail_leggings",
            "link_recipe": "true"
        },
        {
            "type": "patchouli:spotlight",
            "item":"minecraft:chainmail_boots",
            "link_recipe": "true"
        }
             ]
}
