{    
    "name": "Barrels",
    "icon": "crumbs:oak_barrel",
    "category": "patchouli:utility",
    "sortnum": 0,
    "advancement": "endernomicon:planks",
    "pages": [
        {
            "type": "patchouli:crafting",
            "recipe": "crumbs:oak_barrel",
            "text": "$(li)The Barrel is a good alternative from the common $(l:patchouli:utility/vanilla/chest)Chests$(/l).$(br)$(li)It has the same capacity but it can be opened even if a block is on top of it.",  
            "link_recipe": "true"
        },
        {
            "type": "patchouli:small_pictures",
            "picture": "endermonicon:textures/book/entries/utility/barrels.png",
            "text": "$(li)Just place the block and right click on them to open their inventory."
        },
        {
            "type": "patchouli:crafting",
            "recipe": "crumbs:dark_oak_barrel",
            "recipe2": "crumbs:birch_barrel",
            "link_recipe": "true"
        },
        {
            "type": "patchouli:crafting",
            "recipe": "crumbs:jungle_barrel",
            "recipe2": "crumbs:acacia_barrel",
            "link_recipe": "true"
        },
        {
            "type": "patchouli:crafting",
            "recipe": "crumbs:crimson_barrel",
            "recipe2": "crumbs:warped_barrel",
            "link_recipe": "true"
        },
        {
            "type": "patchouli:empty_page"
        }
             ]
}
