{    
    "name": "Fletching Table",
    "icon": "minecraft:fletching_table",
    "category": "patchouli:utility",
    "sortnum": 0,
    "advancement": "endernomicon:fletching_table",
    "pages": [
        {
            "type": "patchouli:crafting",
            "recipe": "minecraft:fletching_table",
            "text": "$(li)The Fletching Table is a placeable block that does not have any kind of right-click functionality.$(br)$(li)If a $(l:patchouli:villagers/villager)Villager$(/l) is located near a Honey Pot, it will turn into an $(l:patchouli:villagers/fletcher)Fletcher$(/l)."
        },
        {
            "type": "patchouli:empty_page"
        }
             ]
}
