{    
    "name": "Block (Ignitium)",
    "icon": "cataclysm:ignitium_block",
    "category": "patchouli:utility",
    "sortnum": 0,
    "advancement": "endernomicon:ignitium_ingot",
    "pages": [
        {
            "type": "patchouli:crafting",
            "recipe": "kubejs:kjs_2joxo0e1v04swu9bi7jaoxhuu",
            "text": "$(li)Ignitium Block is a new decorative block.$(br)$(li)It can be used to save $(l:patchouli:miscellaneous/cataclysm/ignitium_ingot)Ignitium Ingot$(/l) in a more efficient way.",  
            "link_recipe": "true"
        },
        {
            "type": "patchouli:empty_page"
        }
             ]
}
