{    
    "name": "City (End)",
    "icon": "minecraft:purpur_block",
    "category": "patchouli:structures",
    "sortnum": 0,
    "advancement": "minecraft:end/find_end_city",
    "pages": [
        {
            "type": "patchouli:text",
            "text": "$(li)The End City is a big structure that can be found in the End.$(br)$(li)This place is inhabited mainly by $(l:patchouli:creatures/vanilla/shulker)Shulkers$(/l) and $(l:patchouli:creatures/alexsmobs/mimicube)Mimicubes$(/l)."
        },
        {
            "type": "patchouli:small_pictures",
            "picture": "endermonicon:textures/book/entries/structures/end_city.png"

        }
             ]
}