{    
    "name": "Safe",
    "icon": "supplementaries:safe",
    "category": "patchouli:utility",
    "sortnum": 0,
    "advancement": "endernomicon:safe",
    "pages": [
        {
            "type": "smithing_table",
            "title": "Safe",
            "input": "minecraft:shulker_box",
            "input2": "minecraft:netherite_ingot",
            "output": "supplementaries:safe",
            "text": "$(li)Safes can be used to save items in a safe way.$(br)$(li)They are immune to fire and they have two different modes.",
            "link_recipe": "true"
        },
        {
            "type": "patchouli:text",
            "title": "Simple Mode",
            "text": "$(li)By default, Safes will be bound to the first person that places it / opens and unbound one.$(br)$(li)Other persons won't be able to open a safe and they will not be able to break it."
        },
        {
            "type": "patchouli:text",
            "title": "Key Mode",
            "text": "$(li)You can craft a $(l:patchouli:tools/supplementaries/key)Key$(/l) and change it's name in an $(l:patchouli:utility/vanilla/anvil)Anvil$(/l).$(br)$(li)Then, if you click on a Safe with this key, the safe will be bound to this key name and will only be able to be oppened when you have a key with the same name in the inventory."
        },
        {
            "type": "patchouli:empty_page"
        }
             ]
}
