{    
    "name": "Woodcutter & Sawmill",
    "icon": "charm:woodcutter",
    "category": "patchouli:utility",
    "sortnum": 0,
    "advancement": "minecraft:story/smelt_iron",
    "pages": [
        {
            "type": "patchouli:crafting",
            "recipe": "charm:woodcutters/woodcutter",
            "text": "$(li)The Woodcutter is a new block that adds more efficient crafts recipes for wood items.",
            "link_recipe": "true"
        },
        {
            "type": "patchouli:small_pictures",
            "picture": "endermonicon:textures/book/entries/utility/woodcutter_1.png",
            "text": "$(li)If this block is placed near of a Villager without a job, it will be turned into a $(l:patchouli:villagers/lumberjack)Lumberjack$(/l)."
        },
        {
            "type": "patchouli:small_pictures",
            "picture": "endermonicon:textures/book/entries/utility/woodcutter_2.png",
            "text": "$(li)Just insert the Wood Planks or Logs that you want to transform inside, select the block that do you want and save it in your inventory."
        },
        {
            "type": "patchouli:crafting",
            "recipe": "environmental:crafting/sawmill",
            "text": "$(li)The Sawmill is a other good block that adds more efficient recipes for crafing Wood items.",
            "link_recipe": "true"
        },
        {
            "type": "patchouli:small_pictures",
            "picture": "endermonicon:textures/book/entries/utility/woodcutter_3.png",
            "text": "$(li)If this block is placed near of a Villager without a job, it will be turned into a $(l:patchouli:villagers/carpenter)Carpenter$(/l)."
        },
        {
            "type": "patchouli:small_pictures",
            "picture": "endermonicon:textures/book/entries/utility/woodcutter_4.png",
            "text": "$(li)Just insert the Wood Planks or Logs that you want to transform inside, select the block that do you want and save it in your inventory."
        }
             ]
}
