{    
    "name": "Sunflower Plains",
    "icon": "minecraft:grass_block",
    "category": "patchouli:biomes",
    "sortnum": 0,
    "advancement": "endernomicon:sunflower_plains",
    "pages": [
        {
            "type": "patchouli:text",
            "text": "$(li)Sunflower Plains are a variant of the $(l:patchouli:biomes/overworld/grass/plains)Plains$(/l) biome.$(br)$(li)They can be found in the Overworld.$(br)$(li)In this place you can find flowers such as Sunflowers, Buttercups and Cornflowers.$(br)$(li)$(l:patchouli:pets/alexsmobs/hummingbird)Hummingbirds$(/l) can be found flying around here pollinating the flowers of this biome."
        },
        {
            "type": "patchouli:text",
            "text": "$(li)You can search this biome by typing the words $(l)Sunflower Plains$() in the search box of the $(l:patchouli:perks/natures_compass)Nature's Compass$(/l)."
        },
        {
            "type": "patchouli:pictures",
            "picture": "endermonicon:textures/book/entries/biomes/sunflower_plains.png",
            "transparency": "endermonicon:textures/book/templates/pictures/center_30.png"
        },
        {
            "type": "patchouli:empty",
            "draw_filler": false
        }
             ]
}
