{    
    "name": "Wolf Armor (Diamond)",
    "icon": "revampedwolf:diamond_wolf_armor",
    "category": "patchouli:pets",
    "sortnum": 0,
#    "advancement": "endrem:main/nether_eye",
    "pages": [
        {
            "type": "patchouli:crafting",
            "recipe": "revampedwolf:diamond_wolf_armor",
            "text": "$(li)The Diamond Wolf Armor is the upgrade of the Golden Wolf Armor that you can equip to your tamed Fox or Foxhound.$(br)$(li)You can craft it placing Diamonds and Diamond Boots in a Crafting Table.",
            "link_recipe": "true"
        }
             ]
}
