{    
    "name": "Shovel (Gold)",
    "icon": "minecraft:golden_shovel",
    "category": "patchouli:tools",
    "sortnum": 0,
    "advancement": "endernomicon:gold_ingot",
    "pages": [
        {
            "type": "patchouli:crafting",
            "recipe": "minecraft:golden_shovel",
            "text": "$(li)The Golden Shovel is the worst shovel that you can have because its durability is the lowest compared to other shovels." ,
            "link_recipe": "true"
        },
        {
            "type": "patchouli:entity",
            "name": "Golden Shovel",
            "entity": "minecraft:armor_stand{ShowArms:1b,NoBasePlate:1b,HandItems:[{id:golden_shovel,Count:1}],HandDropChances:[0f]}",
            "scale": 0.9,
            "text": "The Golden Shovel has even less durabiliy than the Wooden Shovel." 
        }
             ]
}
