{    
    "name": "Beams",
    "icon": "decorative_blocks:oak_beam",
    "category": "patchouli:decoration",
    "sortnum": 0,
    "advancement": "endernomicon:logs",
    "pages": [
        {
            "type": "patchouli:small_pictures",
            "picture": "endermonicon:textures/book/entries/decoration/beams.png",
            "text": "$(li)Beams are a new wood block for decoration purposes."
        },
        {
            "type": "patchouli:crafting",
            "recipe": "decorative_blocks:oak_beam",
            "recipe2": "decorative_blocks_abnormals:river_beam"
        },
        {
            "type": "patchouli:crafting",
            "recipe": "decorative_blocks:birch_beam",
            "recipe2": "decorative_blocks:jungle_beam"
        },
        {
            "type": "patchouli:crafting",
            "recipe": "decorative_blocks:dark_oak_beam",
            "recipe2": "decorative_blocks:acacia_beam"
        },
        {
            "type": "patchouli:crafting",
            "recipe": "decorative_blocks:spruce_beam",
            "recipe2": "decorative_blocks_abnormals:yucca_beam"
        },
        {
            "type": "patchouli:crafting",
            "recipe": "decorative_blocks_abnormals:brown_mushroom_beam",
            "recipe2": "decorative_blocks_abnormals:cypress_beam"
        },
        {
            "type": "patchouli:crafting",
            "recipe": "decorative_blocks_abnormals:willow_beam",
            "recipe2": "decorative_blocks_abnormals:driftwood_beam"
        },
        {
            "type": "patchouli:crafting",
            "recipe": "decorative_blocks_abnormals:rosewood_beam",
            "recipe2": "decorative_blocks_abnormals:maple_beam"
        },
        {
            "type": "patchouli:crafting",
            "recipe": "decorative_blocks_abnormals:red_mushroom_beam",
            "recipe2": "decorative_blocks_abnormals:morado_beam"
        },
        {
            "type": "patchouli:crafting",
            "recipe": "decorative_blocks_abnormals:cherry_beam"
        },
        {
            "type": "patchouli:crafting",
            "recipe": "decorative_blocks:crimson_beam",
            "recipe2": "decorative_blocks:warped_beam"
        },
        {
            "type": "patchouli:crafting",
            "recipe2": "decorative_blocks_abnormals:poise_beam"
        }
             ]
}
