{    
    "name": "Blaze",
    "icon": "minecraft:netherrack",
    "category": "patchouli:creatures",
    "sortnum": 0,
#    "advancement": "endrem:main/nether_eye",
    "pages": [
        {
            "type": "patchouli:text",
            "text": "$(li)Blaze are floating hostile creatures that can be found in the Nether Fortresses of the Nether.$(br)$(li)They throw you Fireballs, if one of these hits you, it will burns you, inflincting an extra damage for a few seconds.$(br)$(li)They may drop Blaze Rods on death."
        },
        {
            "type": "patchouli:entity",
            "entity": "minecraft:blaze",
            "scale": 1
        }
             ]
}
